odoo/addons/survey_certification_py3o/README.rst
odoo/addons/survey_certification_py3o/__init__.py
odoo/addons/survey_certification_py3o/__manifest__.py
odoo/addons/survey_certification_py3o/controllers/__init__.py
odoo/addons/survey_certification_py3o/controllers/main.py
odoo/addons/survey_certification_py3o/demo/demo_report_certification.odt
odoo/addons/survey_certification_py3o/i18n/it.po
odoo/addons/survey_certification_py3o/i18n/survey_certification_py3o.pot
odoo/addons/survey_certification_py3o/models/__init__.py
odoo/addons/survey_certification_py3o/models/mail_template.py
odoo/addons/survey_certification_py3o/models/py3o_report.py
odoo/addons/survey_certification_py3o/models/survey_survey.py
odoo/addons/survey_certification_py3o/models/survey_user_input.py
odoo/addons/survey_certification_py3o/readme/CONTRIBUTORS.md
odoo/addons/survey_certification_py3o/readme/DESCRIPTION.md
odoo/addons/survey_certification_py3o/readme/USAGE.md
odoo/addons/survey_certification_py3o/static/description/icon.png
odoo/addons/survey_certification_py3o/static/description/index.html
odoo/addons/survey_certification_py3o/tests/__init__.py
odoo/addons/survey_certification_py3o/tests/test_survey_certification_py3o.py
odoo/addons/survey_certification_py3o/views/survey_reports.xml
odoo/addons/survey_certification_py3o/views/survey_survey_views.xml
odoo_addon_survey_certification_py3o-17.0.1.0.0.4.dist-info/METADATA
odoo_addon_survey_certification_py3o-17.0.1.0.0.4.dist-info/WHEEL
odoo_addon_survey_certification_py3o-17.0.1.0.0.4.dist-info/top_level.txt
odoo_addon_survey_certification_py3o-17.0.1.0.0.4.dist-info/RECORD
